httpclient_logging/__init__.py
httpclient_logging/patch.py
httpclient_logging-1.0.dist-info/METADATA
httpclient_logging-1.0.dist-info/WHEEL
httpclient_logging-1.0.dist-info/entry_points.txt
httpclient_logging-1.0.dist-info/RECORD
