Metadata-Version: 2.1
Name: httpclient-logging
Version: 1.0
Summary:  python-package
Home-page: https://github.com/libranet/httpclient_logging
License: MIT
Keywords: entrypoints,sitecustomize,httpclient,logging
Author: Wouter Vanden Hove
Author-email: wouter@libranet.eu
Maintainer: Wouter Vanden Hove
Maintainer-email: wouter@libranet.eu
Requires-Python: >=3.8.0,<4.0
Classifier: Development Status :: 4 - Beta
Classifier: Environment :: Console
Classifier: Intended Audience :: Developers
Classifier: License :: OSI Approved :: MIT License
Classifier: Operating System :: POSIX :: Linux
Classifier: Programming Language :: Python :: 3
Classifier: Programming Language :: Python :: 3.8
Classifier: Programming Language :: Python :: 3.9
Classifier: Programming Language :: Python :: 3.10
Classifier: Programming Language :: Python :: 3.11
Classifier: Programming Language :: Python :: 3.10
Classifier: Programming Language :: Python :: 3.11
Classifier: Programming Language :: Python :: 3.8
Classifier: Programming Language :: Python :: 3.9
Classifier: Programming Language :: Python :: Implementation :: CPython
Classifier: Typing :: Typed
Requires-Dist: sitecustomize-entrypoints (>=0.1.0)
Project-URL: Changelog, https://github.com/libranet/httpclient-logging/releases
Project-URL: Documentation, https://httpclient-logging.readthedocs.io
Project-URL: Issues, https://github.com/libranet/httpclient-logging/issues
Project-URL: Repository, https://github.com/libranet/httpclient_logging
